constellate/__init__.py
constellate/charts.py
constellate/client.py
constellate_client-0.1.0.dist-info/LICENSE
constellate_client-0.1.0.dist-info/METADATA
constellate_client-0.1.0.dist-info/WHEEL
constellate_client-0.1.0.dist-info/RECORD
