Metadata-Version: 2.1
Name: constellate-client
Version: 0.1.0
Summary: Client library for constellate.org
Home-page: https://constellate.org
Author: Ian DesJardins
Author-email: ian.desjardins@ithaka.org
Requires-Python: >=3.9
Classifier: Programming Language :: Python :: 3
Classifier: Programming Language :: Python :: 3.9
Classifier: Programming Language :: Python :: 3.10
Classifier: Programming Language :: Python :: 3.11
Requires-Dist: progressbar (>=2.5,<3.0)
Requires-Dist: requests (>=2.31.0,<3.0.0)
Project-URL: Repository, https://github.com/ithaka/tdm
